{
    "groundTextureUrl": "./textures/ground.jpg",
    "wallTextureUrl": "./textures/wall.jpg",

   "rooms": [
        {
            "name": "Room 1",
            "lenght": 10,
            "width": 10,
            "bedX": 0.01,
            "bedY": 0.01,
            "isActive": 1
        },
        {
            "name": "Room 2",
            "lenght": 15,
            "width": 10,
            "bedX": 0.01,
            "bedY": 0.01,
            "isActive": 1
        },
        {
            "name": "Room 3",
            "lenght": 10,
            "width": 10,
            "bedX": 0.01,
            "bedY": 0.01,
            "isActive": 0
        },
        {
            "name": "Room 4",
            "lenght": 10,
            "width": 10,
            "bedX": 0.01,
            "bedY": 0.01,
            "isActive": 0
        },
        {
            "name": "Room 5",
            "lenght": 10,
            "width": 10,
            "bedX": 0.01,
            "bedY": 0.01,
            "isActive": 0
        },
        {
            "name": "Room 6",
            "lenght": 10,
            "width": 10,
            "bedX": 0.01,
            "bedY": 0.01,
            "isActive": 0
        },
        {
            "name": "Room 7",
            "lenght": 10,
            "width": 10,
            "bedX": 0.01,
            "bedY": 0.01,
            "isActive": 0
        }
    ]
}